<?xml version = '1.0' encoding = 'UTF-8'?>
<FKIndexAssociation class="oracle.dbtools.crest.model.design.relational.FKIndexAssociation" directorySegmentName="seg_0" id="15E033D7-58B0-DC64-323A-55AE6E178CD6" containerWithKeyObject="1A9B04D8-E8CA-FE2F-9C8A-64030AB0A2C3" localFKIndex="5E10DF21-C328-9B10-DFF1-F6200DC26BB7" name="EMP_MANAGER_FK">
<sourceConnName>ora1</sourceConnName>
<sourceObjSchema>ORA1</sourceObjSchema>
<sourceObjName>EMP_MANAGER_FK</sourceObjName>
<createdBy>dreimann</createdBy>
<createdTime>2018-11-08 08:26:21 UTC</createdTime>
<ownerDesignName>HR_Modeller_View01</ownerDesignName>
<referredTableLongName>ORA1.EMPLOYEES</referredTableLongName>
<deleteRule>NO ACTION</deleteRule>
<referredTableID>1A9B04D8-E8CA-FE2F-9C8A-64030AB0A2C3</referredTableID>
<keyObject>75E5D3CB-4E75-881D-A86B-C5664B446B19</keyObject>
<referredKeyID>75E5D3CB-4E75-881D-A86B-C5664B446B19</referredKeyID>
<mandatory>false</mandatory>
<refColNames>EMPLOYEE_ID</refColNames>
<transferable>true</transferable>
<rely>false</rely>
<columnDependencyConstraintGenerateInDDL>true</columnDependencyConstraintGenerateInDDL>
</FKIndexAssociation>